zedcode/__init__.py
zedcode-0.2.dist-info/LICENSE.txt
zedcode-0.2.dist-info/METADATA
zedcode-0.2.dist-info/WHEEL
zedcode-0.2.dist-info/top_level.txt
zedcode-0.2.dist-info/RECORD
