Metadata-Version: 2.1
Name: zedcode
Version: 0.2
Summary: Shorten your code !
Home-page: UNKNOWN
Author: Kishan Mishra
Author-email: mishrakishan2017@gmail.com
License: UNKNOWN
Platform: UNKNOWN
Classifier: Programming Language :: Python :: 3
Classifier: License :: OSI Approved :: MIT License
Classifier: Operating System :: OS Independent
License-File: LICENSE.txt
